{
    "version": "1.7.0",
    "description": "kernel mode mouse accel",
    "homepage": "https://github.com/a1xd/rawaccel",
    "license": "MIT",
    "url": "https://github.com/a1xd/rawaccel/releases/download/v1.7.0/RawAccel_v1.7.0.zip#/dl.7z",
    "hash": "57fbafbc1da5b43579ad777fa1f6327cd1cea319940cf2bf63e6ab56bcbd1da1",
    "architecture": {
        "64bit": {
            "extract_dir": "RawAccel"
        }
    },
    "shortcuts": [
        [
            "installer.exe",
            "Raw Accel Installer"
        ],
        [
            "uninstaller.exe",
            "Raw Accel Uninstaller"
        ],
        [
            "rawaccel.exe",
            "Raw Accel"
        ]
    ],
    "checkver": "github",
    "persist": "settings.json",
    "autoupdate": {
        "url": "https://github.com/a1xd/rawaccel/releases/download/v$version/RawAccel_v$version.zip#/dl.7z"
    }
}
